README.md
setup.cfg
setup.py
plotify/__init__.py
plotify/custom_plots.py
plotify/plot.py
plotify/smoothing.py
plotify/wandb_plots.py
plotify.egg-info/PKG-INFO
plotify.egg-info/SOURCES.txt
plotify.egg-info/dependency_links.txt
plotify.egg-info/requires.txt
plotify.egg-info/top_level.txt