Metadata-Version: 1.1
Name: plotify
Version: 0.1.17
Summary: Make beautiful plots, fast.
Home-page: http://www.seba1511.com
Author: Seb Arnold
Author-email: smr.arnold@gmail.com
License: License :: OSI Approved :: Apache Software License
Download-URL: https://github.com/seba-1511/plotify/archive/0.1.17.zip
Platform: UNKNOWN
